blackjack21/__init__.py
blackjack21/dealer.py
blackjack21/deck.py
blackjack21/exceptions.py
blackjack21/players.py
blackjack21/table.py
blackjack21/utils.py
blackjack21-4.0.0.dist-info/licenses/LICENSE
blackjack21-4.0.0.dist-info/METADATA
blackjack21-4.0.0.dist-info/WHEEL
blackjack21-4.0.0.dist-info/top_level.txt
blackjack21-4.0.0.dist-info/RECORD
