Metadata-Version: 2.4
Name: blackjack21
Version: 4.0.0
Summary: A complete package for blackjack, with no players limit on a table, double down, and split features too.
Home-page: https://blackjack21.rtfd.io/en/latest/
Author: Rahul Nanwani
Author-email: rahulnanwani@icloud.com
License: MIT
Project-URL: Documentation, https://blackjack21.rtfd.io/en/latest/
Project-URL: Source, https://github.com/rahul-nanwani/blackjack21/
Project-URL: Tracker, https://github.com/rahul-nanwani/blackjack21/issues
Classifier: Development Status :: 5 - Production/Stable
Classifier: License :: OSI Approved :: MIT License
Classifier: Programming Language :: Python :: 3.8
Classifier: Programming Language :: Python :: 3.9
Classifier: Programming Language :: Python :: 3.10
Classifier: Programming Language :: Python :: 3.11
Classifier: Programming Language :: Python :: 3.12
Classifier: Programming Language :: Python :: 3.13
Classifier: Programming Language :: Python :: 3.14
Classifier: Programming Language :: Python :: 3.15
Classifier: Intended Audience :: Developers
Classifier: Operating System :: OS Independent
Classifier: Topic :: Games/Entertainment
License-File: LICENSE
Dynamic: author
Dynamic: author-email
Dynamic: classifier
Dynamic: description
Dynamic: description-content-type
Dynamic: home-page
Dynamic: license
Dynamic: license-file
Dynamic: project-url
Dynamic: summary
